{"cameraMode":{"drawMode":0,"name":"Shaded","section":"Shading Mode"},"sceneLighting":true,"audioPlay":false,"sceneViewState":{"m_AlwaysRefresh":false,"showFog":true,"showSkybox":true,"showFlares":true,"showImageEffects":true,"showParticleSystems":true,"showVisualEffectGraphs":true,"m_FxEnabled":true},"in2DMode":false,"pivot":{"x":9.07514476776123,"y":-1.226278305053711,"z":-2.058833360671997},"rotation":{"x":-0.06838856637477875,"y":-0.9171805381774902,"z":0.17972314357757569,"w":-0.3490067422389984},"size":12.179403305053711,"orthographic":false}